d4_pyclient/__init__.py
d4_pyclient/d4_client.py
d4_pyclient-0.1.7.dist-info/LICENSE
d4_pyclient-0.1.7.dist-info/WHEEL
d4_pyclient-0.1.7.dist-info/METADATA
d4_pyclient-0.1.7.dist-info/RECORD
