Metadata-Version: 2.1
Name: d4-pyclient
Version: 0.1.7
Summary: D4 core software client in Python
Home-page: https://github.com/D4-project/d4-pyclient
License: BSD-2-Clause
Author: Aurelien Thirion (Terrtia)
Author-email: aurelien.thirion@circl.lu
Requires-Python: >=3.6,<4.0
Classifier: License :: OSI Approved :: BSD License
Classifier: Programming Language :: Python :: 3
Classifier: Programming Language :: Python :: 3.6
Classifier: Programming Language :: Python :: 3.7
Classifier: Programming Language :: Python :: 3.8
Project-URL: Repository, https://github.com/D4-project/d4-pyclient
